PyCSPSolver/__init__.py
PyCSPSolver/constraint.py
PyCSPSolver/csp.py
PyCSPSolver-0.0.1.dist-info/LICENSE
PyCSPSolver-0.0.1.dist-info/METADATA
PyCSPSolver-0.0.1.dist-info/WHEEL
PyCSPSolver-0.0.1.dist-info/top_level.txt
PyCSPSolver-0.0.1.dist-info/RECORD
