Metadata-Version: 2.1
Name: PyCSPSolver
Version: 0.0.1
Home-page: https://github.com/nobodyPerfecZ/py-csp-solver
Author: ['Dennis J.', 'Patrick B.']
Requires-Python: >=3.10
License-File: LICENSE
